gui_master_pygame/Button.py
gui_master_pygame/Container.py
gui_master_pygame/EntryBox.py
gui_master_pygame/Image.py
gui_master_pygame/Label.py
gui_master_pygame/Text.py
gui_master_pygame/__init__.py
gui_master-0.0.2.dist-info/METADATA
gui_master-0.0.2.dist-info/WHEEL
gui_master-0.0.2.dist-info/top_level.txt
gui_master-0.0.2.dist-info/RECORD
